[
  {
    "1": 453
  },
  {
    "1": 147
  },
  {
    "1": 166
  },
  {
    "1": 204
  },
  {
    "1": 189
  },
  {
    "1": 181
  },
  {
    "1": 204
  },
  {
    "1": 188
  },
  {
    "1": 125
  },
  {
    "1": 167
  },
  {
    "1": 103
  },
  {
    "1": 103
  },
  {
    "1": 167
  },
  {
    "1": 221
  },
  {
    "1": 177
  },
  {
    "1": 221
  },
  {
    "1": 118
  },
  {
    "1": 88
  },
  {
    "1": 63
  },
  {
    "1": 132
  },
  {
    "1": 135
  },
  {
    "1": 67
  },
  {
    "1": 78
  },
  {
    "1": 100
  },
  {
    "1": 93
  },
  {
    "1": 57
  },
  {
    "1": 82
  },
  {
    "1": 137
  },
  {
    "1": 57
  },
  {
    "1": 301
  },
  {
    "1": 257
  },
  {
    "1": 129
  },
  {
    "1": 98
  },
  {
    "1": 245
  },
  {
    "1": 105
  },
  {
    "1": 122
  },
  {
    "1": 172
  },
  {
    "1": 111
  },
  {
    "1": 101
  },
  {
    "1": 96
  },
  {
    "1": 95
  },
  {
    "1": 89
  },
  {
    "1": 71
  },
  {
    "1": 104
  },
  {
    "1": 44
  },
  {
    "1": 107
  },
  {
    "1": 135
  },
  {
    "1": 62
  },
  {
    "1": 41
  },
  {
    "1": 6
  },
  {
    "1": 17
  },
  {
    "1": 68
  },
  {
    "1": 429
  },
  {
    "1": 97
  },
  {
    "1": 88
  },
  {
    "1": 80
  },
  {
    "1": 135
  },
  {
    "1": 297
  },
  {
    "1": 161
  },
  {
    "1": 157
  },
  {
    "1": 1447
  },
  {
    "1": 648
  },
  {
    "1": 129
  },
  {
    "1": 102
  },
  {
    "1": 210
  },
  {
    "1": 555
  },
  {
    "1": 123
  },
  {
    "1": 120
  },
  {
    "1": 97
  },
  {
    "1": 98
  },
  {
    "1": 84
  },
  {
    "1": 118
  },
  {
    "1": 97
  },
  {
    "1": 150
  },
  {
    "1": 237
  },
  {
    "1": 737
  },
  {
    "1": 74
  },
  {
    "1": 105
  },
  {
    "1": 96
  },
  {
    "1": 85
  },
  {
    "1": 81
  },
  {
    "1": 88
  },
  {
    "1": 80
  },
  {
    "1": 109
  },
  {
    "1": 80
  },
  {
    "1": 106
  },
  {
    "1": 59
  },
  {
    "1": 124
  },
  {
    "1": 139
  },
  {
    "1": 226
  },
  {
    "1": 120
  },
  {
    "1": 79
  },
  {
    "1": 116
  },
  {
    "1": 122
  },
  {
    "1": 244
  },
  {
    "1": 59
  },
  {
    "1": 30
  },
  {
    "1": 58
  },
  {
    "1": 50
  },
  {
    "1": 58
  },
  {
    "1": 43
  },
  {
    "1": 19
  },
  {
    "1": 36
  },
  {
    "1": 107
  },
  {
    "1": 235
  },
  {
    "1": 202
  },
  {
    "1": 64
  },
  {
    "1": 71
  },
  {
    "1": 68
  },
  {
    "1": 198
  },
  {
    "1": 68
  },
  {
    "1": 97
  },
  {
    "1": 159
  },
  {
    "1": 82
  },
  {
    "1": 104
  },
  {
    "1": 122
  },
  {
    "1": 116
  },
  {
    "1": 114
  },
  {
    "1": 102
  },
  {
    "1": 157
  },
  {
    "1": 115
  },
  {
    "1": 111
  },
  {
    "1": 331
  },
  {
    "1": 73
  },
  {
    "1": 104
  },
  {
    "1": 149
  },
  {
    "1": 106
  },
  {
    "1": 100
  },
  {
    "1": 126
  },
  {
    "1": 277
  },
  {
    "1": 106
  },
  {
    "1": 106
  },
  {
    "1": 109
  },
  {
    "1": 121
  },
  {
    "1": 128
  },
  {
    "1": 88
  },
  {
    "1": 73
  },
  {
    "1": 52
  }
]